netip.py
netip-1.0.0.dist-info/WHEEL
netip-1.0.0.dist-info/METADATA
netip-1.0.0.dist-info/RECORD
